sanic_jwt_extended/__init__.py
sanic_jwt_extended/decorators.py
sanic_jwt_extended/exceptions.py
sanic_jwt_extended/jwt_manager.py
sanic_jwt_extended/tokens.py
sanic_jwt_extended/utils.py
sanic_jwt_extended-0.4.4.dist-info/LICENSE
sanic_jwt_extended-0.4.4.dist-info/WHEEL
sanic_jwt_extended-0.4.4.dist-info/METADATA
sanic_jwt_extended-0.4.4.dist-info/RECORD
