Metadata-Version: 2.1
Name: sanic-jwt-extended
Version: 0.4.4
Summary: Extended JWT integration with Sanic
Home-page: https://github.com/NovemberOscar/Sanic-JWT-Extended
License: MIT
Keywords: sanic,jwt,json web token
Author: Seonghyeon Kim
Author-email: kim@seonghyeon.dev
Requires-Python: >=3.6,<4.0
Classifier: Environment :: Web Environment
Classifier: Intended Audience :: Developers
Classifier: License :: OSI Approved :: MIT License
Classifier: Operating System :: OS Independent
Classifier: Programming Language :: Python :: 3
Classifier: Programming Language :: Python :: 3.6
Classifier: Programming Language :: Python :: 3.7
Classifier: Topic :: Internet :: WWW/HTTP :: Dynamic Content
Classifier: Topic :: Software Development :: Libraries :: Python Modules
Requires-Dist: PyJWT (>=1.6.4,<2.0.0)
Requires-Dist: sanic (>=0.7.0,<0.8.0)
Project-URL: Documentation, https://sanic-jwt-extended.readthedocs.io/en/latest/
Project-URL: Repository, https://github.com/NovemberOscar/Sanic-JWT-Extended
